[
  {
    "url": "https://www.monterrey.gob.mx/transparencia/Oficial/ControlUrbano22.asp",
    "label": "Febrero",
    "documentos": [
      {
        "title": "L-000045-21",
        "link": "https://www.monterrey.gob.mx/pdf/Hipervinculos/Sedue/CU22/L-000045-21.pdf"
      }
    ]
  },
  {
    "url": "https://www.monterrey.gob.mx/transparencia/Oficial/ControlUrbano22.asp",
    "label": "Marzo",
    "documentos": [
      {
        "title": "L-000045-21",
        "link": "https://www.monterrey.gob.mx/pdf/Hipervinculos/Sedue/CU22/L-000045-21.pdf"
      }
    ]
  },
  {
    "url": "https://www.monterrey.gob.mx/transparencia/Oficial/ControlUrbano22.asp",
    "label": "Abril",
    "documentos": [
      {
        "title": "L-000045-21",
        "link": "https://www.monterrey.gob.mx/pdf/Hipervinculos/Sedue/CU22/L-000045-21.pdf"
      }
    ]
  },
  {
    "url": "https://www.monterrey.gob.mx/transparencia/Oficial/ControlUrbano22.asp",
    "label": "Mayo",
    "documentos": [
      {
        "title": "L-000045-21",
        "link": "https://www.monterrey.gob.mx/pdf/Hipervinculos/Sedue/CU22/L-000045-21.pdf"
      }
    ]
  },
  {
    "url": "https://www.monterrey.gob.mx/transparencia/Oficial/ControlUrbano22.asp",
    "label": "Junio",
    "documentos": [
      {
        "title": "L-000045-21",
        "link": "https://www.monterrey.gob.mx/pdf/Hipervinculos/Sedue/CU22/L-000045-21.pdf"
      }
    ]
  },
  {
    "url": "https://www.monterrey.gob.mx/transparencia/Oficial/ControlUrbano22.asp",
    "label": "Julio",
    "documentos": [
      {
        "title": "L-000045-21",
        "link": "https://www.monterrey.gob.mx/pdf/Hipervinculos/Sedue/CU22/L-000045-21.pdf"
      }
    ]
  },
  {
    "url": "https://www.monterrey.gob.mx/transparencia/Oficial/ControlUrbano22.asp",
    "label": "Agosto",
    "documentos": [
      {
        "title": "L-000045-21",
        "link": "https://www.monterrey.gob.mx/pdf/Hipervinculos/Sedue/CU22/L-000045-21.pdf"
      }
    ]
  },
  {
    "url": "https://www.monterrey.gob.mx/transparencia/Oficial/ControlUrbano22.asp",
    "label": "Septiembre",
    "documentos": [
      {
        "title": "L-000045-21",
        "link": "https://www.monterrey.gob.mx/pdf/Hipervinculos/Sedue/CU22/L-000045-21.pdf"
      }
    ]
  },
  {
    "url": "https://www.monterrey.gob.mx/transparencia/Oficial/ControlUrbano22.asp",
    "label": "Octubre",
    "documentos": [
      {
        "title": "L-000045-21",
        "link": "https://www.monterrey.gob.mx/pdf/Hipervinculos/Sedue/CU22/L-000045-21.pdf"
      }
    ]
  },
  {
    "url": "https://www.monterrey.gob.mx/transparencia/Oficial/ControlUrbano22.asp",
    "label": "Noviembre",
    "documentos": [
      {
        "title": "L-000045-21",
        "link": "https://www.monterrey.gob.mx/pdf/Hipervinculos/Sedue/CU22/L-000045-21.pdf"
      }
    ]
  },
  {
    "url": "https://www.monterrey.gob.mx/transparencia/Oficial/ControlUrbano22.asp",
    "label": "Diciembre",
    "documentos": [
      {
        "title": "L-000045-21",
        "link": "https://www.monterrey.gob.mx/pdf/Hipervinculos/Sedue/CU22/L-000045-21.pdf"
      }
    ]
  }
]